tigerente/__init__.py
tigerente/__main__.py
tigerente/ble/__init__.py
tigerente/ble/bleio.py
tigerente/ble/sync.py
tigerente/cli.py
tigerente/com/comm.py
tigerente/com/common.py
tigerente/daemon.py
tigerente/usb/__init__.py
tigerente/usb/flasher.py
tigerente/util/build.py
tigerente/util/custom_types.py
tigerente/util/random_namegen.py
tigerente/util/storage.py
tigerente/version.py
tigerente-0.5.1.dist-info/WHEEL
tigerente-0.5.1.dist-info/entry_points.txt
tigerente-0.5.1.dist-info/METADATA
tigerente-0.5.1.dist-info/RECORD
