Metadata-Version: 2.3
Name: tigerente
Version: 0.5.1
Summary: Add your description here
Requires-Dist: bleak>=2.0.0
Requires-Dist: click>=8.3.1
Requires-Dist: mpy-cross>=1.26.1.post2
Requires-Dist: pyserial>=3.5
Requires-Dist: pyyaml>=6.0.3
Requires-Dist: requests>=2.32.5
Requires-Dist: rich>=14.2.0
Requires-Dist: watchdog>=6.0.0
Requires-Python: >=3.12
